mycalc/calculator.py
ZiTa67-0.0.1.dist-info/METADATA
ZiTa67-0.0.1.dist-info/WHEEL
ZiTa67-0.0.1.dist-info/top_level.txt
ZiTa67-0.0.1.dist-info/RECORD
