Metadata-Version: 2.1
Name: ZiTa67
Version: 0.0.1
Summary: oss-calculator
Home-page: https://github.com/BaeZiTa/ZiTa
Download-URL: https://github/BaeZiTa/ZiTa/archive/refs/tags/v0.0.1.zip
Author: Bae Jun Yeong
License: UNKNOWN
Platform: UNKNOWN
Classifier: Programming Language :: Python :: 3
